LICENSE.txt
NOTICE
README.md
setup.py
tests/__init__.py
tests/test_HeisenbergBonded.py
tests/test_HeisenbergXYZ.py
tests/test_Ising.py
timeseries_qmc/__init__.py
timeseries_qmc.egg-info/PKG-INFO
timeseries_qmc.egg-info/SOURCES.txt
timeseries_qmc.egg-info/dependency_links.txt
timeseries_qmc.egg-info/not-zip-safe
timeseries_qmc.egg-info/requires.txt
timeseries_qmc.egg-info/top_level.txt
timeseries_qmc/boltzmann/__init__.py
timeseries_qmc/boltzmann/_approximate.py
timeseries_qmc/boltzmann/_calculator.py
timeseries_qmc/boltzmann/_exact.py
timeseries_qmc/boltzmann/_fourier.py
timeseries_qmc/boltzmann/_nnls.py
timeseries_qmc/boltzmann/_numerics.py
timeseries_qmc/loschmidt/__init__.py
timeseries_qmc/loschmidt/_cache.py
timeseries_qmc/loschmidt/_catstate.py
timeseries_qmc/loschmidt/_evaluator.py
timeseries_qmc/loschmidt/_exact.py
timeseries_qmc/loschmidt/_hadamard.py
timeseries_qmc/loschmidt/_trotter.py
timeseries_qmc/mitigation/__init__.py
timeseries_qmc/mitigation/_fidelity.py
timeseries_qmc/mitigation/_spam.py
timeseries_qmc/mitigation/_symmetry.py
timeseries_qmc/models/__init__.py
timeseries_qmc/models/_circuits.py
timeseries_qmc/models/_heisenberg.py
timeseries_qmc/models/_ising.py
timeseries_qmc/models/_model.py
timeseries_qmc/sampling/__init__.py
timeseries_qmc/sampling/_cluster.py
timeseries_qmc/sampling/_markov.py
timeseries_qmc/sampling/_sampler.py
timeseries_qmc/sampling/_single.py
timeseries_qmc/utils/__init__.py
timeseries_qmc/utils/_bitstring.py
timeseries_qmc/utils/_lattice.py
timeseries_qmc/utils/_logging.py