Metadata-Version: 2.1
Name: timeseries-qmc
Version: 0.1.0
Summary: A Python package for running the time series QMC algorithm
Author: Quantinuum GmbH
Author-email: khaldoon.ghanem@quantinuum.com
License: Apache License 2.0
Project-URL: Documentation, https://cqcl.github.io/timeseries-qmc/build/html/index.html
Project-URL: Source, https://github.com/CQCL/timeseries-qmc
Classifier: Development Status :: 4 - Beta
Classifier: Intended Audience :: Science/Research
Classifier: License :: OSI Approved :: Apache Software License
Classifier: Operating System :: POSIX :: Linux
Classifier: Operating System :: MacOS :: MacOS X
Classifier: Programming Language :: Python :: 3
License-File: LICENSE.txt
License-File: NOTICE
